Metadata-Version: 2.4
Name: fast-django-asgi
Version: 0.1.3.post1
Summary: Django-like developer experience on ASGI powered by FastAPI, Tortoise ORM, Aerich, and FastAPI-Admin.
Author: Aakar Sharma
License: MIT
License-File: LICENSE
Keywords: admin,aerich,asgi,django,fastapi,tortoise-orm
Classifier: Framework :: AsyncIO
Classifier: Framework :: FastAPI
Classifier: Intended Audience :: Developers
Classifier: License :: OSI Approved :: MIT License
Classifier: Programming Language :: Python :: 3
Classifier: Programming Language :: Python :: 3 :: Only
Classifier: Programming Language :: Python :: 3.11
Classifier: Programming Language :: Python :: 3.12
Classifier: Topic :: Software Development :: Libraries
Classifier: Typing :: Typed
Requires-Python: >=3.11
Requires-Dist: aerich>=0.7.2
Requires-Dist: email-validator>=2.1.0
Requires-Dist: fastapi-admin>=1.0.4
Requires-Dist: fastapi>=0.115
Requires-Dist: jinja2>=3.1
Requires-Dist: passlib[bcrypt]>=1.7.4
Requires-Dist: pydantic-settings>=2.2.1
Requires-Dist: pydantic>=2.5
Requires-Dist: python-multipart>=0.0.9
Requires-Dist: tortoise-orm>=0.20
Requires-Dist: typer>=0.12.3
Requires-Dist: uvicorn[standard]>=0.30
Provides-Extra: dev
Requires-Dist: ipython; extra == 'dev'
Requires-Dist: mypy>=1.10; extra == 'dev'
Requires-Dist: pre-commit>=3.7; extra == 'dev'
Requires-Dist: ruff>=0.5; extra == 'dev'
Requires-Dist: types-pyyaml; extra == 'dev'
Provides-Extra: docs
Requires-Dist: mkdocs-include-markdown-plugin>=6.0; extra == 'docs'
Requires-Dist: mkdocs-material>=9.5; extra == 'docs'
Requires-Dist: mkdocs>=1.6; extra == 'docs'
Requires-Dist: mkdocstrings[python]>=0.24; extra == 'docs'
Provides-Extra: test
Requires-Dist: anyio>=4.4; extra == 'test'
Requires-Dist: httpx>=0.27; extra == 'test'
Requires-Dist: pytest-asyncio>=0.23; extra == 'test'
Requires-Dist: pytest-cov>=5.0; extra == 'test'
Requires-Dist: pytest>=8.2; extra == 'test'
